{
  "notes": [
    {
      "id": 1,
      "noteText": "This person seems suspicious",
      "timestamp": 1584382255712,
      "criminal": "Taurean Bins"
    },
    {
      "noteText": "Madi is suspicious",
      "criminal": "Madi Peper",
      "timestamp": 1584384742515,
      "id": 3
    },
    {
      "noteText": "I am not it",
      "criminal": "Shady Grant",
      "timestamp": 1584388757306,
      "id": 4
    },
    {
      "noteText": "He's not it",
      "criminal": "John J",
      "timestamp": 1584461194051,
      "id": 5
     }
     ]}